{
  "$schema": "https://apify.com/schemas/v1/actor.ide.json",
  "actorSpecification": 1,
  "name": "aws-ip-range-diff",
  "title": "AWS IP Range Change Detector",
  "description": "Tracks AWS ip-ranges.json between runs and emits added, removed, and unchanged IP ranges as structured records. Useful for network security teams, cloud firewall automation, and infrastructure monitoring.",
  "version": "1.0",
  "meta": {
    "templateId": "python-crawlee-cheerio",
    "generatedBy": "Dandy/Hermes Agent",
    "category": "networking"
  },
  "pricing": {
    "pricePerEvent": [
      {
        "eventType": "range_entry",
        "price": 3
      },
      {
        "eventType": "snapshot",
        "price": 6
      }
    ],
    "pricingInfo": "Pay-per-Event: $0.03 per detected IP range row, $0.06 per snapshot crawl."
  },
  "input": "./input_schema.json",
  "output": "./output_schema.json"
}
